setup.py
hjutils/__init__.py
hjutils/hjutils.py
hjutils/image_storage.py
hjutils.egg-info/PKG-INFO
hjutils.egg-info/SOURCES.txt
hjutils.egg-info/dependency_links.txt
hjutils.egg-info/not-zip-safe
hjutils.egg-info/top_level.txt