Metadata-Version: 1.0
Name: hjutils
Version: 0.4.1
Summary: clinical trial information retriver
Home-page: https://github.com/kobyant/hjutils
Author: jing
Author-email: jinghedeveloper@163.com
License: MIT
Platform: UNKNOWN
